Step2/d_ff.v
// Step2/d_ff.v
module d_ff (
    input clk,      // 하드웨어의 심장박동
    input rst_n,    // 리셋 (0일 때 초기화)
    input d,        // 입력
    output reg q    // 출력 (기억된 값)
);
    // posedge clk: 클럭이 0에서 1로 올라가는 순간에만 작동!
    always @(posedge clk or negedge rst_n) begin
        if (!rst_n) begin
            q <= 1'b0;
        end else begin
            q <= d;
        end
    end
endmodule

Step2/tb_d_ff.v
`timescale 1ns/1ps

module tb_d_ff;
    reg clk;
    reg rst_n;
    reg d;
    wire q;

    // 1. 설계한 D-FF 모듈 불러오기 (Instantiate)
    d_ff uut (
        .clk(clk),
        .rst_n(rst_n),
        .d(d),
        .q(q)
    );

    // 2. 클럭 생성: 10ns 주기로 0과 1을 반복 (100MHz)
    initial clk = 0;
    always #5 clk = ~clk; 

    initial begin
        // 파형 저장 설정
        $dumpfile("step2.vcd");
        $dumpvars(0, tb_d_ff);

        // 3. 초기화 (Reset)
        // 하드웨어는 시작할 때 반드시 리셋을 해서 초기 상태를 잡아줘야 합니다.
        rst_n = 0; d = 0;
        #12;             // 12ns 동안 리셋 유지
        rst_n = 1;       // 리셋 해제
        #10;

        // 4. 데이터 입력 및 타이밍 관찰
        d = 1; #10;      // d를 1로 바꿈
        d = 0; #10;      // d를 0으로 바꿈
        d = 1; #5;       // 클럭이 치기 직전에 d를 1로 바꿈 (아슬아슬한 타이밍)
        #15;
        d = 0; #20;

        $display("Simulation Finished!");
        $finish;
    end
endmodule

Step2/step2.vcd
$date
	Mon Apr  6 09:32:05 2026
$end
$version
	Icarus Verilog
$end
$timescale
	1ps
$end
$scope module tb_d_ff $end
$var wire 1 ! q $end
$var reg 1 " clk $end
$var reg 1 # d $end
$var reg 1 $ rst_n $end
$scope module uut $end
$var wire 1 " clk $end
$var wire 1 # d $end
$var wire 1 $ rst_n $end
$var reg 1 ! q $end
$upscope $end
$upscope $end
$enddefinitions $end
$comment Show the parameter values. $end
$dumpall
$end
#0
$dumpvars
0$
0#
0"
0!
$end
#5000
1"
#10000
0"
#12000
1$
#15000
1"
#20000
0"
#22000
1#
#25000
1!
1"
#30000
0"
#32000
0#
#35000
0!
1"
#40000
0"
#42000
1#
#45000
1!
1"
#50000
0"
#55000
1"
#60000
0"
#62000
0#
#65000
0!
1"
